[{"__type__":"cc.AnimationClip","_name":"1001_gebo_R_ani","_duration":0.36666666666666664,"curveData":{"paths":{"gebo_R_2":{"props":{"position":[{"frame":0.05,"value":[-11.422,-12.827,0]}],"scale":[{"frame":0.05,"value":{"__type__":"cc.Vec2","x":1.304,"y":1.304}},{"frame":0.15,"value":{"__type__":"cc.Vec2","x":1.2128,"y":1.2128}},{"frame":0.18333333333333332,"value":{"__type__":"cc.Vec2","x":1,"y":1}}],"opacity":[{"frame":0,"value":0},{"frame":0.05,"value":255}]}},"gebo_R_1":{"props":{"position":[{"frame":0.23333333333333334,"value":[-29.659,-86.365,0]},{"frame":0.3333333333333333,"value":[-26.5627,-72.52329999999999,0]},{"frame":0.36666666666666664,"value":[-19.338,-40.226,0]}],"opacity":[{"frame":0.18333333333333332,"value":0},{"frame":0.23333333333333334,"value":255}]}}}}},{"__type__":"cc.SpriteFrame","content":{"name":"gebo_R_1","texture":"1e031f384","rect":[227,825,24,27],"offset":[0,0],"originalSize":[24,27],"rotated":1,"capInsets":[0,0,0,0]}},[{"__type__":"cc.Prefab","_name":"1001_gebo_R_ani","data":{"__id__":1}},{"__type__":"cc.Node","_name":"1001_gebo_R_ani","_children":[{"__id__":2},{"__id__":3}],"_components":[{"__type__":"cc.Animation","node":{"__id__":1},"_clips":[{"__uuid__":"5doZ29a/RNwZB5paDV6D8t"}]}],"_prefab":{"__type__":"cc.PrefabInfo","root":{"__id__":1},"asset":{"__uuid__":"a5PnnDbS9OpIEqHnS6PzMd"},"fileId":"01LqLJz6RNj5UilviN+GSI"},"_trs":{"__type__":"TypedArray","ctor":"Float64Array","array":[7.197,15.936,0,0,0,0,1,1,1,1]}},{"__type__":"cc.Node","_name":"gebo_R_2","_parent":{"__id__":1},"_components":[{"__type__":"cc.Sprite","node":{"__id__":2},"_materials":[{"__uuid__":"ecpdLyjvZBwrvm+cedCcQy"}],"_spriteFrame":{"__uuid__":"dbJo072DlG94gZe0aLFOZi"}}],"_prefab":{"__type__":"cc.PrefabInfo","root":{"__id__":1},"asset":{"__uuid__":"a5PnnDbS9OpIEqHnS6PzMd"},"fileId":"3fRAWOu2lDk4d30aOcKjAf"},"_contentSize":{"__type__":"cc.Size","width":40,"height":57},"_trs":{"__type__":"TypedArray","ctor":"Float64Array","array":[-11.422,-12.827,0,0,0,0,1,1,1,1]}},{"__type__":"cc.Node","_name":"gebo_R_1","_parent":{"__id__":1},"_components":[{"__type__":"cc.Sprite","node":{"__id__":3},"_materials":[{"__uuid__":"ecpdLyjvZBwrvm+cedCcQy"}],"_spriteFrame":{"__uuid__":"7dY+fSimpFxIVz47HscKy6"}}],"_prefab":{"__type__":"cc.PrefabInfo","root":{"__id__":1},"asset":{"__uuid__":"a5PnnDbS9OpIEqHnS6PzMd"},"fileId":"4875ECg9JH8bYQpWwroMRf"},"_contentSize":{"__type__":"cc.Size","width":24,"height":27},"_trs":{"__type__":"TypedArray","ctor":"Float64Array","array":[-19.338,-40.226,0,0,0,0,1,1,1,1]}}],{"__type__":"cc.SpriteFrame","content":{"name":"gebo_R_2","texture":"1e031f384","rect":[135,779,40,57],"offset":[0,0],"originalSize":[40,57],"rotated":1,"capInsets":[0,0,0,0]}}]