[{"__type__":"cc.SpriteFrame","content":{"name":"jianjia_L_1","texture":"1d108a12d","rect":[156,506,65,68],"offset":[0,0],"originalSize":[65,68],"rotated":1,"capInsets":[0,0,0,0]}},[{"__type__":"cc.Prefab","_name":"1006_jianjia_L_ani","data":{"__id__":1}},{"__type__":"cc.Node","_name":"1006_jianjia_L_ani","_children":[{"__id__":2},{"__id__":3},{"__id__":4},{"__id__":5}],"_components":[{"__type__":"cc.Animation","node":{"__id__":1},"_clips":[{"__uuid__":"df9K3/c+JB/K+kjSZwJ/xn"}]}],"_prefab":{"__type__":"cc.PrefabInfo","root":{"__id__":1},"asset":{"__uuid__":"80c1a2dnFLVZCzpqBhg2d7"},"fileId":"7fDUfWtWZJiYrIfPbohtAy"},"_trs":{"__type__":"TypedArray","ctor":"Float64Array","array":[-25,5,0,0,0,0,1,1,1,1]}},{"__type__":"cc.Node","_name":"jianjia_L_4","_parent":{"__id__":1},"_components":[{"__type__":"cc.Sprite","node":{"__id__":2},"_materials":[{"__uuid__":"ecpdLyjvZBwrvm+cedCcQy"}],"_spriteFrame":{"__uuid__":"b4hyWqmKVMdatedmtURlmA"}}],"_prefab":{"__type__":"cc.PrefabInfo","root":{"__id__":1},"asset":{"__uuid__":"80c1a2dnFLVZCzpqBhg2d7"},"fileId":"eajwYl6RVNnJanpgRKEo72"},"_contentSize":{"__type__":"cc.Size","width":41,"height":47},"_trs":{"__type__":"TypedArray","ctor":"Float64Array","array":[49.274,-29.773,0,0,0,0,1,1,1,1]}},{"__type__":"cc.Node","_name":"jianjia_L_3","_parent":{"__id__":1},"_components":[{"__type__":"cc.Sprite","node":{"__id__":3},"_materials":[{"__uuid__":"ecpdLyjvZBwrvm+cedCcQy"}],"_spriteFrame":{"__uuid__":"bc9dUuFiROmKnLlNc9fzbn"}}],"_prefab":{"__type__":"cc.PrefabInfo","root":{"__id__":1},"asset":{"__uuid__":"80c1a2dnFLVZCzpqBhg2d7"},"fileId":"820erhtAxLRJ/0/zIsNBS3"},"_contentSize":{"__type__":"cc.Size","width":104,"height":90},"_trs":{"__type__":"TypedArray","ctor":"Float64Array","array":[38.228,-13.028,0,0,0,0,1,1,1,1]}},{"__type__":"cc.Node","_name":"jianjia_L_2","_parent":{"__id__":1},"_components":[{"__type__":"cc.Sprite","node":{"__id__":4},"_materials":[{"__uuid__":"ecpdLyjvZBwrvm+cedCcQy"}],"_spriteFrame":{"__uuid__":"aefKwL12RNs5L+JJPNfNCr"}}],"_prefab":{"__type__":"cc.PrefabInfo","root":{"__id__":1},"asset":{"__uuid__":"80c1a2dnFLVZCzpqBhg2d7"},"fileId":"81ygvHAABBnZk9wdzDN7nL"},"_contentSize":{"__type__":"cc.Size","width":37,"height":55},"_trs":{"__type__":"TypedArray","ctor":"Float64Array","array":[-4.722,-6.529,0,0,0,0,1,1,1,1]}},{"__type__":"cc.Node","_name":"jianjia_L_1","_parent":{"__id__":1},"_components":[{"__type__":"cc.Sprite","node":{"__id__":5},"_materials":[{"__uuid__":"ecpdLyjvZBwrvm+cedCcQy"}],"_spriteFrame":{"__uuid__":"05itoqGBpOvojOT59N+W+N"}}],"_prefab":{"__type__":"cc.PrefabInfo","root":{"__id__":1},"asset":{"__uuid__":"80c1a2dnFLVZCzpqBhg2d7"},"fileId":"feYM1JYOZORZ0mx6EmgYVA"},"_contentSize":{"__type__":"cc.Size","width":65,"height":68},"_trs":{"__type__":"TypedArray","ctor":"Float64Array","array":[34.895,-13.903,0,0,0,0,1,1,1,1]}}],{"__type__":"cc.SpriteFrame","content":{"name":"jianjia_L_2","texture":"1d108a12d","rect":[3,774,37,55],"offset":[0,0],"originalSize":[37,55],"rotated":1,"capInsets":[0,0,0,0]}},{"__type__":"cc.SpriteFrame","content":{"name":"jianjia_L_4","texture":"1d108a12d","rect":[180,848,41,47],"offset":[0,0],"originalSize":[41,47],"rotated":1,"capInsets":[0,0,0,0]}},{"__type__":"cc.SpriteFrame","content":{"name":"jianjia_L_3","texture":"1d108a12d","rect":[114,3,104,90],"offset":[0,0],"originalSize":[104,90],"capInsets":[0,0,0,0]}},{"__type__":"cc.AnimationClip","_name":"1006_jianjia_L_ani","_duration":0.6,"curveData":{"paths":{"jianjia_L_1":{"props":{"position":[{"frame":0.2,"value":[50.597,-1.056,0]},{"frame":0.26666666666666666,"value":[45.36300000000001,-5.338333333333332,0]},{"frame":0.3,"value":[34.895,-13.903,0]}],"scale":[{"frame":0.2,"value":{"__type__":"cc.Vec2","x":1.523,"y":1.523}},{"frame":0.26666666666666666,"value":{"__type__":"cc.Vec2","x":1.3486666666666667,"y":1.3486666666666667}},{"frame":0.3,"value":{"__type__":"cc.Vec2","x":1,"y":1}}],"opacity":[{"frame":0.15,"value":0},{"frame":0.2,"value":255}]}},"jianjia_L_2":{"props":{"position":[{"frame":0.35,"value":[-26.134,1.084,0]},{"frame":0.4166666666666667,"value":[-18.996666666666663,-1.4536666666666687,0]},{"frame":0.45,"value":[-4.722,-6.529,0]}],"scale":[{"frame":0.35,"value":{"__type__":"cc.Vec2","x":1.536,"y":1.536}},{"frame":0.4166666666666667,"value":{"__type__":"cc.Vec2","x":1.3573333333333333,"y":1.3573333333333333}},{"frame":0.45,"value":{"__type__":"cc.Vec2","x":1,"y":1}}],"opacity":[{"frame":0.3,"value":0},{"frame":0.35,"value":255}]}},"jianjia_L_3":{"props":{"position":[{"frame":0.15,"value":[38.228,-13.028,0]}],"scale":[{"frame":0.05,"value":{"__type__":"cc.Vec2","x":1.566,"y":1.566}},{"frame":0.11666666666666667,"value":{"__type__":"cc.Vec2","x":1.3773333333333333,"y":1.3773333333333333}},{"frame":0.15,"value":{"__type__":"cc.Vec2","x":1,"y":1}}],"opacity":[{"frame":0,"value":0},{"frame":0.05,"value":255}]}},"jianjia_L_4":{"props":{"position":[{"frame":0.5,"value":[22.628,-2.175,0]},{"frame":0.5666666666666667,"value":[31.510000000000005,-11.37433333333334,0]},{"frame":0.6,"value":[49.274,-29.773,0]}],"scale":[{"frame":0.5,"value":{"__type__":"cc.Vec2","x":0.873,"y":0.873}},{"frame":0.5666666666666667,"value":{"__type__":"cc.Vec2","x":0.9153333333333333,"y":0.9153333333333333}},{"frame":0.6,"value":{"__type__":"cc.Vec2","x":1,"y":1}}],"opacity":[{"frame":0.45,"value":0},{"frame":0.5,"value":255}]}}}}}]