[[{"__type__":"cc.Prefab","_name":"shouji","data":{"__id__":1}},{"__type__":"cc.Node","_name":"shouji","_children":[{"__id__":2}],"_components":[{"__type__":"cc.Animation","node":{"__id__":1},"_defaultClip":{"__uuid__":"e7rVqojjpH5rcufGxxoo6B"},"_clips":[{"__uuid__":"e7rVqojjpH5rcufGxxoo6B"}]}],"_prefab":{"__type__":"cc.PrefabInfo","root":{"__id__":1},"asset":{"__id__":0},"fileId":"44AiIM6HRGM7OX7x/NaM9U"},"_trs":{"__type__":"TypedArray","ctor":"Float64Array","array":[0,0,0,0,0,0,1,1,1,1]}},{"__type__":"cc.Node","_name":"Hit","_parent":{"__id__":1},"_children":[{"__id__":3},{"__id__":4}],"_prefab":{"__type__":"cc.PrefabInfo","root":{"__id__":1},"asset":{"__id__":0},"fileId":"a5R7vAiu1Cxq9jYCtI3lXo"},"_trs":{"__type__":"TypedArray","ctor":"Float64Array","array":[0,0,0,0,0,0,1,1.5,1.5,1]}},{"__type__":"cc.Node","_name":"shouji","_parent":{"__id__":2},"_components":[{"__type__":"cc.Sprite","node":{"__id__":3},"_materials":[{"__uuid__":"ecpdLyjvZBwrvm+cedCcQy"}],"_spriteFrame":{"__uuid__":"c3iD1gviFI2r4os8//bOUo"}}],"_prefab":{"__type__":"cc.PrefabInfo","root":{"__id__":1},"asset":{"__id__":0},"fileId":"f4VVLzYLxN5J54GTV5K3VN"},"_opacity":0,"_contentSize":{"__type__":"cc.Size","width":128,"height":128},"_trs":{"__type__":"TypedArray","ctor":"Float64Array","array":[0,0,0,0,0,0,1,1,1,1]}},{"__type__":"cc.Node","_name":"baokaici","_parent":{"__id__":2},"_components":[{"__type__":"cc.Sprite","node":{"__id__":4},"_materials":[{"__uuid__":"ecpdLyjvZBwrvm+cedCcQy"}],"_spriteFrame":{"__uuid__":"43pdzEqhpFV4rnlf/C3JZ8"}}],"_prefab":{"__type__":"cc.PrefabInfo","root":{"__id__":1},"asset":{"__id__":0},"fileId":"e7DGrphx5He5XHXiEQY5sx"},"_opacity":0,"_contentSize":{"__type__":"cc.Size","width":109,"height":121},"_trs":{"__type__":"TypedArray","ctor":"Float64Array","array":[0,0,0,0,0,0,1,1,1,1]}}],{"__type__":"cc.AnimationClip","_name":"shouji","_duration":0.23333333333333334,"curveData":{"paths":{"Hit/baokaici":{"props":{"opacity":[{"frame":0,"value":0},{"frame":0.016666666666666666,"value":255},{"frame":0.16666666666666666,"value":255},{"frame":0.18333333333333332,"value":0}],"scale":[{"frame":0.05,"value":{"__type__":"cc.Vec2","x":0.5,"y":0.5}},{"frame":0.16666666666666666,"value":{"__type__":"cc.Vec2","x":0.827,"y":0.827}}]}},"Hit/shouji":{"props":{"scale":[{"frame":0.11666666666666667,"value":{"__type__":"cc.Vec2","x":0.627,"y":0.627}},{"frame":0.23333333333333334,"value":{"__type__":"cc.Vec2","x":1.088,"y":1.088}}],"opacity":[{"frame":0.11666666666666667,"value":0},{"frame":0.16666666666666666,"value":255},{"frame":0.23333333333333334,"value":0}]}}}}}]