[{"__type__":"cc.SpriteFrame","content":{"name":"arena_lbl_zhanli","texture":"1ef512264","rect":[390,307,141,25],"offset":[0,0],"originalSize":[141,25],"rotated":1,"capInsets":[0,0,0,0]}},{"__type__":"cc.SpriteFrame","content":{"name":"arena_bg_beijing","texture":"78bTgK5kVEHLRKCbcN6OyR","rect":[0,0,720,1560],"offset":[0,0],"originalSize":[720,1560],"capInsets":[0,0,0,0]}},{"__type__":"cc.SpriteFrame","content":{"name":"arena_btn_heed","texture":"1ef512264","rect":[3,504,223,261],"offset":[0,0],"originalSize":[223,261],"rotated":1,"capInsets":[0,0,0,0]}}]